Workbook

Sheet IMDb Movie
A1: director_name | B1: num_critic_for_reviews | C1: gross | D1: genres | E1: actor_1_name | F1: movie_title | G1: num_voted_users | H1: num_user_for_reviews | I1: language | J1: country | K1: budget | L1: title_year | M1: imdb_score | N1: net_profit | O1: Duration | P1: ROI
A2: James Cameron | B2: 723 | C2: 760505847 | D2: Action|Adventure|Fantasy|Sci-Fi | E2: CCH Pounder | F2: Avatar | G2: 886204 | H2: 3054 | I2: English | J2: USA | K2: 237000000 | L2: 2009 | M2: 7.9 | N2: =IMDB_Table[[#This Row],[gross]]-IMDB_Table[[#This Row],[budget]] -> 523505847 | O2: 178 | P2: =IMDB_Table[[#This Row],[net_profit]]/IMDB_Table[[#This Row],[budget]]*100 -> 220.88854
A3: Gore Verbinski | B3: 302 | C3: 309404152 | D3: Action|Adventure|Fantasy | E3: Johnny Depp | F3: Pirates Of The Caribbean: At World'S End | G3: 471220 | H3: 1238 | I3: English | J3: USA | K3: 300000000 | L3: 2007 | M3: 7.1 | N3: =IMDB_Table[[#This Row],[gross]]-IMDB_Table[[#This Row],[budget]] -> 9404152 | O3: 169 | P3: =IMDB_Table[[#This Row],[net_profit]]/IMDB_Table[[#This Row],[budget]]*100 -> 3.1347173
A4: Sam Mendes | B4: 602 | C4: 200074175 | D4: Action|Adventure|Thriller | E4: Christoph Waltz | F4: Spectre | G4: 275868 | H4: 994 | I4: English | J4: UK | K4: 245000000 | L4: 2015 | M4: 6.8 | N4: =IMDB_Table[[#This Row],[gross]]-IMDB_Table[[#This Row],[budget]] -> -44925825 | O4: 148 | P4: =IMDB_Table[[#This Row],[net_profit]]/IMDB_Table[[#This Row],[budget]]*100 -> -18.337071
A5: Christopher Nolan | B5: 813 | C5: 448130642 | D5: Action|Thriller | E5: Tom Hardy | F5: The Dark Knight Rises | G5: 1144337 | H5: 2701 | I5: English | J5: USA | K5: 250000000 | L5: 2012 | M5: 8.5 | N5: =IMDB_Table[[#This Row],[gross]]-IMDB_Table[[#This Row],[budget]] -> 198130642 | O5: 164 | P5: =IMDB_Table[[#This Row],[net_profit]]/IMDB_Table[[#This Row],[budget]]*100 -> 79.252257
A6: Andrew Stanton | B6: 462 | C6: 73058679 | D6: Action|Adventure|Sci-Fi | E6: Daryl Sabara | F6: John Carter | G6: 212204 | H6: 738 | I6: English | J6: USA | K6: 263700000 | L6: 2012 | M6: 6.6 | N6: =IMDB_Table[[#This Row],[gross]]-IMDB_Table[[#This Row],[budget]] -> -190641321 | O6: 132 | P6: =IMDB_Table[[#This Row],[net_profit]]/IMDB_Table[[#This Row],[budget]]*100 -> -72.294775
A7: Sam Raimi | B7: 392 | C7: 336530303 | D7: Action|Adventure|Romance | E7: J.K. Simmons | F7: Spider-Man 3 | G7: 383056 | H7: 1902 | I7: English | J7: USA | K7: 258000000 | L7: 2007 | M7: 6.2 | N7: =IMDB_Table[[#This Row],[gross]]-IMDB_Table[[#This Row],[budget]] -> 78530303 | O7: 156 | P7: =IMDB_Table[[#This Row],[net_profit]]/IMDB_Table[[#This Row],[budget]]*100 -> 30.438102
A8: Nathan Greno | B8: 324 | C8: 200807262 | D8: Adventure|Animation|Comedy|Family|Fantasy|Musical|Romance | E8: Brad Garrett | F8: Tangled | G8: 294810 | H8: 387 | I8: English | J8: USA | K8: 260000000 | L8: 2010 | M8: 7.8 | N8: =IMDB_Table[[#This Row],[gross]]-IMDB_Table[[#This Row],[budget]] -> -59192738 | O8: 100 | P8: =IMDB_Table[[#This Row],[net_profit]]/IMDB_Table[[#This Row],[budget]]*100 -> -22.766438
A9: Joss Whedon | B9: 635 | C9: 458991599 | D9: Action|Adventure|Sci-Fi | E9: Chris Hemsworth | F9: Avengers: Age Of Ultron | G9: 462669 | H9: 1117 | I9: English | J9: USA | K9: 250000000 | L9: 2015 | M9: 7.5 | N9: =IMDB_Table[[#This Row],[gross]]-IMDB_Table[[#This Row],[budget]] -> 208991599 | O9: 141 | P9: =IMDB_Table[[#This Row],[net_profit]]/IMDB_Table[[#This Row],[budget]]*100 -> 83.59664
A10: David Yates | B10: 375 | C10: 301956980 | D10: Adventure|Family|Fantasy|Mystery | E10: Alan Rickman | F10: Harry Potter And The Half-Blood Prince | G10: 321795 | H10: 973 | I10: English | J10: UK | K10: 250000000 | L10: 2009 | M10: 7.5 | N10: =IMDB_Table[[#This Row],[gross]]-IMDB_Table[[#This Row],[budget]] -> 51956980 | O10: 153 | P10: =IMDB_Table[[#This Row],[net_profit]]/IMDB_Table[[#This Row],[budget]]*100 -> 20.782792
A11: Zack Snyder | B11: 673 | C11: 330249062 | D11: Action|Adventure|Sci-Fi | E11: Henry Cavill | F11: Batman V Superman: Dawn Of Justice | G11: 371639 | H11: 3018 | I11: English | J11: USA | K11: 250000000 | L11: 2016 | M11: 6.9 | N11: =IMDB_Table[[#This Row],[gross]]-IMDB_Table[[#This Row],[budget]] -> 80249062 | O11: 183 | P11: =IMDB_Table[[#This Row],[net_profit]]/IMDB_Table[[#This Row],[budget]]*100 -> 32.099625
A12: Bryan Singer | B12: 434 | C12: 200069408 | D12: Action|Adventure|Sci-Fi | E12: Kevin Spacey | F12: Superman Returns | G12: 240396 | H12: 2367 | I12: English | J12: USA | K12: 209000000 | L12: 2006 | M12: 6.1 | N12: =IMDB_Table[[#This Row],[gross]]-IMDB_Table[[#This Row],[budget]] -> -8930592 | O12: 169 | P12: =IMDB_Table[[#This Row],[net_profit]]/IMDB_Table[[#This Row],[budget]]*100 -> -4.2730105
A13: Marc Forster | B13: 403 | C13: 168368427 | D13: Action|Adventure | E13: Giancarlo Giannini | F13: Quantum Of Solace | G13: 330784 | H13: 1243 | I13: English | J13: UK | K13: 200000000 | L13: 2008 | M13: 6.7 | N13: =IMDB_Table[[#This Row],[gross]]-IMDB_Table[[#This Row],[budget]] -> -31631573 | O13: 106 | P13: =IMDB_Table[[#This Row],[net_profit]]/IMDB_Table[[#This Row],[budget]]*100 -> -15.815787
... A3784: Jon Gunn | B3784: 43 | C3784: 85222 | D3784: Documentary | E3784: John August | F3784: My Date With Drew | G3784: 4285 | H3784: 84 | I3784: English | J3784: USA | K3784: 1100 | L3784: 2004 | M3784: 6.6 | N3784: =IMDB_Table[[#This Row],[gross]]-IMDB_Table[[#This Row],[budget]] -> 84122 | O3784: 90 | P3784: =IMDB_Table[[#This Row],[net_profit]]/IMDB_Table[[#This Row],[budget]]*100 -> 7647.4545

Sheet Genre Analysis
A1: Genre Analysis
G3: KPI
A5: movie_title | B5: imdb_score | C5: Genre | F5: Total Movies | G5: Highest Profit | H5: Avg Ratings | I5: Avg Duration | J5: Total Genre
A6: Avatar | B6: 7.9 | C6: Action | F6: =COUNTA(IMDB_Table[director_name]) -> 3783 | G6: =MAX(IMDB_Table[net_profit]) -> 523505847 | H6: =AVERAGE(IMDB_Table[imdb_score]) -> 6.4615913 | I6: {=AVERAGE(IMDB_Table[Duration])} -> 109.82712 | J6: =COUNTA(_xlfn.UNIQUE(Movie_analysis_table[Genre])) -> 23
A7: Avatar | B7: 7.9 | C7: Adventure
A8: Avatar | B8: 7.9 | C8: Fantasy
A9: Avatar | B9: 7.9 | C9: Sci-Fi
A10: Pirates Of The Caribbean: At World'S End | B10: 7.1 | C10: Action
A11: Pirates Of The Caribbean: At World'S End | B11: 7.1 | C11: Adventure
A12: Pirates Of The Caribbean: At World'S End | B12: 7.1 | C12: Fantasy
A13: Spectre | B13: 6.8 | C13: Action
A14: Spectre | B14: 6.8 | C14: Adventure
A15: Spectre | B15: 6.8 | C15: Thriller
A16: The Dark Knight Rises | B16: 8.5 | C16: Action
A17: The Dark Knight Rises | B17: 8.5 | C17: Thriller
A18: John Carter | B18: 6.6 | C18: Action
... A11220: My Date With Drew | B11220: 6.6 | C11220: Documentary

Sheet Analysis_1
S2: IMDB Score Analysis based on Genre | AE2: TOP 10 Movies by IMDB ratings Movie Count more than 50
S4: Movies | T4: Count | U4: Mean | V4: Median | W4: Mode | X4: Max | Y4: Min | Z4: Var | AA4: Std | AE4: Movies | AF4: Count | AG4: IMDB
S5: Drama | T5: 1911 | U5: =AVERAGEIF(Movie_analysis_table[Genre],Analysis_1!S5,Movie_analysis_table[imdb_score]) -> 6.7891156 | V5: {=MEDIAN(_xlfn._xlws.FILTER(Movie_analysis_table[imdb_score],Movie_analysis_table[Genre]=Analysis_1!S5))} -> 6.9 | W5: {=IFERROR(_xlfn.MODE.SNGL(_xlfn._xlws.FILTER(Movie_analysis_table[imdb_score],Movie_analysis_table[Genre]=Analysis_1!S5)),0)} -> 6.7 | X5: {=IFERROR(MAX(_xlfn._xlws.FILTER(Movie_analysis_table[imdb_score],Movie_analysis_table[Genre]=Analysis_1!S5)),0)} -> 9.3 | Y5: {=IFERROR(MIN(_xlfn._xlws.FILTER(Movie_analysis_table[imdb_score],Movie_analysis_table[Genre]=Analysis_1!S5)),0)} -> 2.1 | Z5: {=IFERROR(VAR(_xlfn._xlws.FILTER(Movie_analysis_table[imdb_score],Movie_analysis_table[Genre]=Analysis_1!S5)),0)} -> 0.79399665 | AA5: {=IFERROR(_xlfn.STDEV.P(_xlfn._xlws.FILTER(Movie_analysis_table[imdb_score],Movie_analysis_table[Genre]=Analysis_1!S5)),0)} -> 0.89083173 | AE5: {=_xlfn.TAKE(_xlfn._xlws.SORT(_xlfn._xlws.FILTER(S5:U27,T5:T27>=50),3,-1),10)} -> Biography | AF5: 242 | AG5: 7.1400826
S6: Comedy | T6: 1492 | U6: =AVERAGEIF(Movie_analysis_table[Genre],Analysis_1!S6,Movie_analysis_table[imdb_score]) -> 6.183311 | V6: {=MEDIAN(_xlfn._xlws.FILTER(Movie_analysis_table[imdb_score],Movie_analysis_table[Genre]=Analysis_1!S6))} -> 6.3 | W6: {=IFERROR(_xlfn.MODE.SNGL(_xlfn._xlws.FILTER(Movie_analysis_table[imdb_score],Movie_analysis_table[Genre]=Analysis_1!S6)),0)} -> 6.3 | X6: {=IFERROR(MAX(_xlfn._xlws.FILTER(Movie_analysis_table[imdb_score],Movie_analysis_table[Genre]=Analysis_1!S6)),0)} -> 8.8 | Y6: {=IFERROR(MIN(_xlfn._xlws.FILTER(Movie_analysis_table[imdb_score],Movie_analysis_table[Genre]=Analysis_1!S6)),0)} -> 1.9 | Z6: {=IFERROR(VAR(_xlfn._xlws.FILTER(Movie_analysis_table[imdb_score],Movie_analysis_table[Genre]=Analysis_1!S6)),0)} -> 1.0814316 | AA6: {=IFERROR(_xlfn.STDEV.P(_xlfn._xlws.FILTER(Movie_analysis_table[imdb_score],Movie_analysis_table[Genre]=Analysis_1!S6)),0)} -> 1.0395705 | AE6: History | AF6: 152 | AG6: 7.1315789
S7: Thriller | T7: 1084 | U7: =AVERAGEIF(Movie_analysis_table[Genre],Analysis_1!S7,Movie_analysis_table[imdb_score]) -> 6.3748155 | V7: {=MEDIAN(_xlfn._xlws.FILTER(Movie_analysis_table[imdb_score],Movie_analysis_table[Genre]=Analysis_1!S7))} -> 6.4 | W7: {=IFERROR(_xlfn.MODE.SNGL(_xlfn._xlws.FILTER(Movie_analysis_table[imdb_score],Movie_analysis_table[Genre]=Analysis_1!S7)),0)} -> 6.5 | X7: {=IFERROR(MAX(_xlfn._xlws.FILTER(Movie_analysis_table[imdb_score],Movie_analysis_table[Genre]=Analysis_1!S7)),0)} -> 9 | Y7: {=IFERROR(MIN(_xlfn._xlws.FILTER(Movie_analysis_table[imdb_score],Movie_analysis_table[Genre]=Analysis_1!S7)),0)} -> 2.7 | Z7: {=IFERROR(VAR(_xlfn._xlws.FILTER(Movie_analysis_table[imdb_score],Movie_analysis_table[Genre]=Analysis_1!S7)),0)} -> 0.93924512 | AA7: {=IFERROR(_xlfn.STDEV.P(_xlfn._xlws.FILTER(Movie_analysis_table[imdb_score],Movie_analysis_table[Genre]=Analysis_1!S7)),0)} -> 0.96869947 | AE7: War | AF7: 159 | AG7: 7.0484277
S8: Action | T8: 935 | U8: =AVERAGEIF(Movie_analysis_table[Genre],Analysis_1!S8,Movie_analysis_table[imdb_score]) -> 6.2859893 | V8: {=MEDIAN(_xlfn._xlws.FILTER(Movie_analysis_table[imdb_score],Movie_analysis_table[Genre]=Analysis_1!S8))} -> 6.3 | W8: {=IFERROR(_xlfn.MODE.SNGL(_xlfn._xlws.FILTER(Movie_analysis_table[imdb_score],Movie_analysis_table[Genre]=Analysis_1!S8)),0)} -> 6.6 | X8: {=IFERROR(MAX(_xlfn._xlws.FILTER(Movie_analysis_table[imdb_score],Movie_analysis_table[Genre]=Analysis_1!S8)),0)} -> 9 | Y8: {=IFERROR(MIN(_xlfn._xlws.FILTER(Movie_analysis_table[imdb_score],Movie_analysis_table[Genre]=Analysis_1!S8)),0)} -> 2.1 | Z8: {=IFERROR(VAR(_xlfn._xlws.FILTER(Movie_analysis_table[imdb_score],Movie_analysis_table[Genre]=Analysis_1!S8)),0)} -> 1.0781868 | AA8: {=IFERROR(_xlfn.STDEV.P(_xlfn._xlws.FILTER(Movie_analysis_table[imdb_score],Movie_analysis_table[Genre]=Analysis_1!S8)),0)} -> 1.0378023 | AE8: Documentary | AF8: 64 | AG8: 6.99375
S9: Romance | T9: 866 | U9: =AVERAGEIF(Movie_analysis_table[Genre],Analysis_1!S9,Movie_analysis_table[imdb_score]) -> 6.423903 | V9: {=MEDIAN(_xlfn._xlws.FILTER(Movie_analysis_table[imdb_score],Movie_analysis_table[Genre]=Analysis_1!S9))} -> 6.5 | W9: {=IFERROR(_xlfn.MODE.SNGL(_xlfn._xlws.FILTER(Movie_analysis_table[imdb_score],Movie_analysis_table[Genre]=Analysis_1!S9)),0)} -> 6.5 | X9: {=IFERROR(MAX(_xlfn._xlws.FILTER(Movie_analysis_table[imdb_score],Movie_analysis_table[Genre]=Analysis_1!S9)),0)} -> 8.5 | Y9: {=IFERROR(MIN(_xlfn._xlws.FILTER(Movie_analysis_table[imdb_score],Movie_analysis_table[Genre]=Analysis_1!S9)),0)} -> 2.1 | Z9: {=IFERROR(VAR(_xlfn._xlws.FILTER(Movie_analysis_table[imdb_score],Movie_analysis_table[Genre]=Analysis_1!S9)),0)} -> 0.94045689 | AA9: {=IFERROR(_xlfn.STDEV.P(_xlfn._xlws.FILTER(Movie_analysis_table[imdb_score],Movie_analysis_table[Genre]=Analysis_1!S9)),0)} -> 0.96921149 | AE9: Drama | AF9: 1911 | AG9: 6.7891156
S10: Adventure | T10: 766 | U10: =AVERAGEIF(Movie_analysis_table[Genre],Analysis_1!S10,Movie_analysis_table[imdb_score]) -> 6.4549608 | V10: {=MEDIAN(_xlfn._xlws.FILTER(Movie_analysis_table[imdb_score],Movie_analysis_table[Genre]=Analysis_1!S10))} -> 6.6 | W10: {=IFERROR(_xlfn.MODE.SNGL(_xlfn._xlws.FILTER(Movie_analysis_table[imdb_score],Movie_analysis_table[Genre]=Analysis_1!S10)),0)} -> 6.6 | X10: {=IFERROR(MAX(_xlfn._xlws.FILTER(Movie_analysis_table[imdb_score],Movie_analysis_table[Genre]=Analysis_1!S10)),0)} -> 8.9 | Y10: {=IFERROR(MIN(_xlfn._xlws.FILTER(Movie_analysis_table[imdb_score],Movie_analysis_table[Genre]=Analysis_1!S10)),0)} -> 2.3 | Z10: {=IFERROR(VAR(_xlfn._xlws.FILTER(Movie_analysis_table[imdb_score],Movie_analysis_table[Genre]=Analysis_1!S10)),0)} -> 1.2475244 | AA10: {=IFERROR(_xlfn.STDEV.P(_xlfn._xlws.FILTER(Movie_analysis_table[imdb_score],Movie_analysis_table[Genre]=Analysis_1!S10)),0)} -> 1.116197 | AE10: Western | AF10: 58 | AG10: 6.7655172
S11: Crime | T11: 702 | U11: =AVERAGEIF(Movie_analysis_table[Genre],Analysis_1!S11,Movie_analysis_table[imdb_score]) -> 6.5481481 | V11: {=MEDIAN(_xlfn._xlws.FILTER(Movie_analysis_table[imdb_score],Movie_analysis_table[Genre]=Analysis_1!S11))} -> 6.6 | W11: {=IFERROR(_xlfn.MODE.SNGL(_xlfn._xlws.FILTER(Movie_analysis_table[imdb_score],Movie_analysis_table[Genre]=Analysis_1!S11)),0)} -> 6.6 | X11: {=IFERROR(MAX(_xlfn._xlws.FILTER(Movie_analysis_table[imdb_score],Movie_analysis_table[Genre]=Analysis_1!S11)),0)} -> 9.3 | Y11: {=IFERROR(MIN(_xlfn._xlws.FILTER(Movie_analysis_table[imdb_score],Movie_analysis_table[Genre]=Analysis_1!S11)),0)} -> 2.4 | Z11: {=IFERROR(VAR(_xlfn._xlws.FILTER(Movie_analysis_table[imdb_score],Movie_analysis_table[Genre]=Analysis_1!S11)),0)} -> 0.96846304 | AA11: {=IFERROR(_xlfn.STDEV.P(_xlfn._xlws.FILTER(Movie_analysis_table[imdb_score],Movie_analysis_table[Genre]=Analysis_1!S11)),0)} -> 0.98340402 | AE11: Animation | AF11: 197 | AG11: 6.7005076
S12: Fantasy | T12: 496 | U12: =AVERAGEIF(Movie_analysis_table[Genre],Analysis_1!S12,Movie_analysis_table[imdb_score]) -> 6.2850806 | V12: {=MEDIAN(_xlfn._xlws.FILTER(Movie_analysis_table[imdb_score],Movie_analysis_table[Genre]=Analysis_1!S12))} -> 6.4 | W12: {=IFERROR(_xlfn.MODE.SNGL(_xlfn._xlws.FILTER(Movie_analysis_table[imdb_score],Movie_analysis_table[Genre]=Analysis_1!S12)),0)} -> 6.7 | X12: {=IFERROR(MAX(_xlfn._xlws.FILTER(Movie_analysis_table[imdb_score],Movie_analysis_table[Genre]=Analysis_1!S12)),0)} -> 8.9 | Y12: {=IFERROR(MIN(_xlfn._xlws.FILTER(Movie_analysis_table[imdb_score],Movie_analysis_table[Genre]=Analysis_1!S12)),0)} -> 2.2 | Z12: {=IFERROR(VAR(_xlfn._xlws.FILTER(Movie_analysis_table[imdb_score],Movie_analysis_table[Genre]=Analysis_1!S12)),0)} -> 1.3005446 | AA12: {=IFERROR(_xlfn.STDEV.P(_xlfn._xlws.FILTER(Movie_analysis_table[imdb_score],Movie_analysis_table[Genre]=Analysis_1!S12)),0)} -> 1.139264 | AE12: Sport | AF12: 147 | AG12: 6.6013605
S13: Sci-Fi | T13: 484 | U13: =AVERAGEIF(Movie_analysis_table[Genre],Analysis_1!S13,Movie_analysis_table[imdb_score]) -> 6.3272727 | V13: {=MEDIAN(_xlfn._xlws.FILTER(Movie_analysis_table[imdb_score],Movie_analysis_table[Genre]=Analysis_1!S13))} -> 6.4 | W13: {=IFERROR(_xlfn.MODE.SNGL(_xlfn._xlws.FILTER(Movie_analysis_table[imdb_score],Movie_analysis_table[Genre]=Analysis_1!S13)),0)} -> 7 | X13: {=IFERROR(MAX(_xlfn._xlws.FILTER(Movie_analysis_table[imdb_score],Movie_analysis_table[Genre]=Analysis_1!S13)),0)} -> 8.8 | Y13: {=IFERROR(MIN(_xlfn._xlws.FILTER(Movie_analysis_table[imdb_score],Movie_analysis_table[Genre]=Analysis_1!S13)),0)} -> 1.9 | Z13: {=IFERROR(VAR(_xlfn._xlws.FILTER(Movie_analysis_table[imdb_score],Movie_analysis_table[Genre]=Analysis_1!S13)),0)} -> 1.3623188 | AA13: {=IFERROR(_xlfn.STDEV.P(_xlfn._xlws.FILTER(Movie_analysis_table[imdb_score],Movie_analysis_table[Genre]=Analysis_1!S13)),0)} -> 1.1659778 | AE13: Musical | AF13: 102 | AG13: 6.5509804
S14: Family | T14: 441 | U14: =AVERAGEIF(Movie_analysis_table[Genre],Analysis_1!S14,Movie_analysis_table[imdb_score]) -> 6.2 | V14: {=MEDIAN(_xlfn._xlws.FILTER(Movie_analysis_table[imdb_score],Movie_analysis_table[Genre]=Analysis_1!S14))} -> 6.3 | W14: {=IFERROR(_xlfn.MODE.SNGL(_xlfn._xlws.FILTER(Movie_analysis_table[imdb_score],Movie_analysis_table[Genre]=Analysis_1!S14)),0)} -> 5.4 | X14: {=IFERROR(MAX(_xlfn._xlws.FILTER(Movie_analysis_table[imdb_score],Movie_analysis_table[Genre]=Analysis_1!S14)),0)} -> 8.6 | Y14: {=IFERROR(MIN(_xlfn._xlws.FILTER(Movie_analysis_table[imdb_score],Movie_analysis_table[Genre]=Analysis_1!S14)),0)} -> 1.9 | Z14: {=IFERROR(VAR(_xlfn._xlws.FILTER(Movie_analysis_table[imdb_score],Movie_analysis_table[Genre]=Analysis_1!S14)),0)} -> 1.3679091 | AA14: {=IFERROR(_xlfn.STDEV.P(_xlfn._xlws.FILTER(Movie_analysis_table[imdb_score],Movie_analysis_table[Genre]=Analysis_1!S14)),0)} -> 1.1682497 | AE14: Crime | AF14: 702 | AG14: 6.5481481
S15: Horror | T15: 379 | U15: =AVERAGEIF(Movie_analysis_table[Genre],Analysis_1!S15,Movie_analysis_table[imdb_score]) -> 5.9039578 | V15: {=MEDIAN(_xlfn._xlws.FILTER(Movie_analysis_table[imdb_score],Movie_analysis_table[Genre]=Analysis_1!S15))} -> 5.9 | W15: {=IFERROR(_xlfn.MODE.SNGL(_xlfn._xlws.FILTER(Movie_analysis_table[imdb_score],Movie_analysis_table[Genre]=Analysis_1!S15)),0)} -> 6.2 | X15: {=IFERROR(MAX(_xlfn._xlws.FILTER(Movie_analysis_table[imdb_score],Movie_analysis_table[Genre]=Analysis_1!S15)),0)} -> 8.6 | Y15: {=IFERROR(MIN(_xlfn._xlws.FILTER(Movie_analysis_table[imdb_score],Movie_analysis_table[Genre]=Analysis_1!S15)),0)} -> 2.3 | Z15: {=IFERROR(VAR(_xlfn._xlws.FILTER(Movie_analysis_table[imdb_score],Movie_analysis_table[Genre]=Analysis_1!S15)),0)} -> 0.98212715 | AA15: {=IFERROR(_xlfn.STDEV.P(_xlfn._xlws.FILTER(Movie_analysis_table[imdb_score],Movie_analysis_table[Genre]=Analysis_1!S15)),0)} -> 0.989715
S16: Mystery | T16: 376 | U16: =AVERAGEIF(Movie_analysis_table[Genre],Analysis_1!S16,Movie_analysis_table[imdb_score]) -> 6.4718085 | V16: {=MEDIAN(_xlfn._xlws.FILTER(Movie_analysis_table[imdb_score],Movie_analysis_table[Genre]=Analysis_1!S16))} -> 6.5 | W16: {=IFERROR(_xlfn.MODE.SNGL(_xlfn._xlws.FILTER(Movie_analysis_table[imdb_score],Movie_analysis_table[Genre]=Analysis_1!S16)),0)} -> 6.6 | X16: {=IFERROR(MAX(_xlfn._xlws.FILTER(Movie_analysis_table[imdb_score],Movie_analysis_table[Genre]=Analysis_1!S16)),0)} -> 8.6 | Y16: {=IFERROR(MIN(_xlfn._xlws.FILTER(Movie_analysis_table[imdb_score],Movie_analysis_table[Genre]=Analysis_1!S16)),0)} -> 3.1 | Z16: {=IFERROR(VAR(_xlfn._xlws.FILTER(Movie_analysis_table[imdb_score],Movie_analysis_table[Genre]=Analysis_1!S16)),0)} -> 1.0155231 | AA16: {=IFERROR(_xlfn.STDEV.P(_xlfn._xlws.FILTER(Movie_analysis_table[imdb_score],Movie_analysis_table[Genre]=Analysis_1!S16)),0)} -> 1.0063907
S17: Biography | T17: 242 | U17: =AVERAGEIF(Movie_analysis_table[Genre],Analysis_1!S17,Movie_analysis_table[imdb_score]) -> 7.1400826 | V17: {=MEDIAN(_xlfn._xlws.FILTER(Movie_analysis_table[imdb_score],Movie_analysis_table[Genre]=Analysis_1!S17))} -> 7.2 | W17: {=IFERROR(_xlfn.MODE.SNGL(_xlfn._xlws.FILTER(Movie_analysis_table[imdb_score],Movie_analysis_table[Genre]=Analysis_1!S17)),0)} -> 7 | X17: {=IFERROR(MAX(_xlfn._xlws.FILTER(Movie_analysis_table[imdb_score],Movie_analysis_table[Genre]=Analysis_1!S17)),0)} -> 8.9 | Y17: {=IFERROR(MIN(_xlfn._xlws.FILTER(Movie_analysis_table[imdb_score],Movie_analysis_table[Genre]=Analysis_1!S17)),0)} -> 4.5 | Z17: {=IFERROR(VAR(_xlfn._xlws.FILTER(Movie_analysis_table[imdb_score],Movie_analysis_table[Genre]=Analysis_1!S17)),0)} -> 0.50423734 | AA17: {=IFERROR(_xlfn.STDEV.P(_xlfn._xlws.FILTER(Movie_analysis_table[imdb_score],Movie_analysis_table[Genre]=Analysis_1!S17)),0)} -> 0.70862805
S18: Animation | T18: 197 | U18: =AVERAGEIF(Movie_analysis_table[Genre],Analysis_1!S18,Movie_analysis_table[imdb_score]) -> 6.7005076 | V18: {=MEDIAN(_xlfn._xlws.FILTER(Movie_analysis_table[imdb_score],Movie_analysis_table[Genre]=Analysis_1!S18))} -> 6.8 | W18: {=IFERROR(_xlfn.MODE.SNGL(_xlfn._xlws.FILTER(Movie_analysis_table[imdb_score],Movie_analysis_table[Genre]=Analysis_1!S18)),0)} -> 7.3 | X18: {=IFERROR(MAX(_xlfn._xlws.FILTER(Movie_analysis_table[imdb_score],Movie_analysis_table[Genre]=Analysis_1!S18)),0)} -> 8.6 | Y18: {=IFERROR(MIN(_xlfn._xlws.FILTER(Movie_analysis_table[imdb_score],Movie_analysis_table[Genre]=Analysis_1!S18)),0)} -> 2.8 | Z18: {=IFERROR(VAR(_xlfn._xlws.FILTER(Movie_analysis_table[imdb_score],Movie_analysis_table[Genre]=Analysis_1!S18)),0)} -> 0.98729566 | AA18: {=IFERROR(_xlfn.STDEV.P(_xlfn._xlws.FILTER(Movie_analysis_table[imdb_score],Movie_analysis_table[Genre]=Analysis_1!S18)),0)} -> 0.99110242
S19: War | T19: 159 | U19: =AVERAGEIF(Movie_analysis_table[Genre],Analysis_1!S19,Movie_analysis_table[imdb_score]) -> 7.0484277 | V19: {=MEDIAN(_xlfn._xlws.FILTER(Movie_analysis_table[imdb_score],Movie_analysis_table[Genre]=Analysis_1!S19))} -> 7.1 | W19: {=IFERROR(_xlfn.MODE.SNGL(_xlfn._xlws.FILTER(Movie_analysis_table[imdb_score],Movie_analysis_table[Genre]=Analysis_1!S19)),0)} -> 7.1 | X19: {=IFERROR(MAX(_xlfn._xlws.FILTER(Movie_analysis_table[imdb_score],Movie_analysis_table[Genre]=Analysis_1!S19)),0)} -> 8.6 | Y19: {=IFERROR(MIN(_xlfn._xlws.FILTER(Movie_analysis_table[imdb_score],Movie_analysis_table[Genre]=Analysis_1!S19)),0)} -> 4.3 | Z19: {=IFERROR(VAR(_xlfn._xlws.FILTER(Movie_analysis_table[imdb_score],Movie_analysis_table[Genre]=Analysis_1!S19)),0)} -> 0.65238675 | AA19: {=IFERROR(_xlfn.STDEV.P(_xlfn._xlws.FILTER(Movie_analysis_table[imdb_score],Movie_analysis_table[Genre]=Analysis_1!S19)),0)} -> 0.80516066
S20: Music | T20: 159 | U20: =AVERAGEIF(Movie_analysis_table[Genre],Analysis_1!S20,Movie_analysis_table[imdb_score]) -> 6.3716981 | V20: {=MEDIAN(_xlfn._xlws.FILTER(Movie_analysis_table[imdb_score],Movie_analysis_table[Genre]=Analysis_1!S20))} -> 6.5 | W20: {=IFERROR(_xlfn.MODE.SNGL(_xlfn._xlws.FILTER(Movie_analysis_table[imdb_score],Movie_analysis_table[Genre]=Analysis_1!S20)),0)} -> 6.5 | X20: {=IFERROR(MAX(_xlfn._xlws.FILTER(Movie_analysis_table[imdb_score],Movie_analysis_table[Genre]=Analysis_1!S20)),0)} -> 8.5 | Y20: {=IFERROR(MIN(_xlfn._xlws.FILTER(Movie_analysis_table[imdb_score],Movie_analysis_table[Genre]=Analysis_1!S20)),0)} -> 1.6 | Z20: {=IFERROR(VAR(_xlfn._xlws.FILTER(Movie_analysis_table[imdb_score],Movie_analysis_table[Genre]=Analysis_1!S20)),0)} -> 1.4739408 | AA20: {=IFERROR(_xlfn.STDEV.P(_xlfn._xlws.FILTER(Movie_analysis_table[imdb_score],Movie_analysis_table[Genre]=Analysis_1!S20)),0)} -> 1.2102358
S21: History | T21: 152 | U21: =AVERAGEIF(Movie_analysis_table[Genre],Analysis_1!S21,Movie_analysis_table[imdb_score]) -> 7.1315789 | V21: {=MEDIAN(_xlfn._xlws.FILTER(Movie_analysis_table[imdb_score],Movie_analysis_table[Genre]=Analysis_1!S21))} -> 7.2 | W21: {=IFERROR(_xlfn.MODE.SNGL(_xlfn._xlws.FILTER(Movie_analysis_table[imdb_score],Movie_analysis_table[Genre]=Analysis_1!S21)),0)} -> 7.7 | X21: {=IFERROR(MAX(_xlfn._xlws.FILTER(Movie_analysis_table[imdb_score],Movie_analysis_table[Genre]=Analysis_1!S21)),0)} -> 8.9 | Y21: {=IFERROR(MIN(_xlfn._xlws.FILTER(Movie_analysis_table[imdb_score],Movie_analysis_table[Genre]=Analysis_1!S21)),0)} -> 5.5 | Z21: {=IFERROR(VAR(_xlfn._xlws.FILTER(Movie_analysis_table[imdb_score],Movie_analysis_table[Genre]=Analysis_1!S21)),0)} -> 0.45157895 | AA21: {=IFERROR(_xlfn.STDEV.P(_xlfn._xlws.FILTER(Movie_analysis_table[imdb_score],Movie_analysis_table[Genre]=Analysis_1!S21)),0)} -> 0.66978208
S22: Sport | T22: 147 | U22: =AVERAGEIF(Movie_analysis_table[Genre],Analysis_1!S22,Movie_analysis_table[imdb_score]) -> 6.6013605 | V22: {=MEDIAN(_xlfn._xlws.FILTER(Movie_analysis_table[imdb_score],Movie_analysis_table[Genre]=Analysis_1!S22))} -> 6.8 | W22: {=IFERROR(_xlfn.MODE.SNGL(_xlfn._xlws.FILTER(Movie_analysis_table[imdb_score],Movie_analysis_table[Genre]=Analysis_1!S22)),0)} -> 7.2 | X22: {=IFERROR(MAX(_xlfn._xlws.FILTER(Movie_analysis_table[imdb_score],Movie_analysis_table[Genre]=Analysis_1!S22)),0)} -> 8.4 | Y22: {=IFERROR(MIN(_xlfn._xlws.FILTER(Movie_analysis_table[imdb_score],Movie_analysis_table[Genre]=Analysis_1!S22)),0)} -> 2 | Z22: {=IFERROR(VAR(_xlfn._xlws.FILTER(Movie_analysis_table[imdb_score],Movie_analysis_table[Genre]=Analysis_1!S22)),0)} -> 1.0987653 | AA22: {=IFERROR(_xlfn.STDEV.P(_xlfn._xlws.FILTER(Movie_analysis_table[imdb_score],Movie_analysis_table[Genre]=Analysis_1!S22)),0)} -> 1.0446486
S23: Musical | T23: 102 | U23: =AVERAGEIF(Movie_analysis_table[Genre],Analysis_1!S23,Movie_analysis_table[imdb_score]) -> 6.5509804 | V23: {=MEDIAN(_xlfn._xlws.FILTER(Movie_analysis_table[imdb_score],Movie_analysis_table[Genre]=Analysis_1!S23))} -> 6.7 | W23: {=IFERROR(_xlfn.MODE.SNGL(_xlfn._xlws.FILTER(Movie_analysis_table[imdb_score],Movie_analysis_table[Genre]=Analysis_1!S23)),0)} -> 7.1 | X23: {=IFERROR(MAX(_xlfn._xlws.FILTER(Movie_analysis_table[imdb_score],Movie_analysis_table[Genre]=Analysis_1!S23)),0)} -> 8.5 | Y23: {=IFERROR(MIN(_xlfn._xlws.FILTER(Movie_analysis_table[imdb_score],Movie_analysis_table[Genre]=Analysis_1!S23)),0)} -> 2.1 | Z23: {=IFERROR(VAR(_xlfn._xlws.FILTER(Movie_analysis_table[imdb_score],Movie_analysis_table[Genre]=Analysis_1!S23)),0)} -> 1.3076723 | AA23: {=IFERROR(_xlfn.STDEV.P(_xlfn._xlws.FILTER(Movie_analysis_table[imdb_score],Movie_analysis_table[Genre]=Analysis_1!S23)),0)} -> 1.1379156
S24: Documentary | T24: 64 | U24: =AVERAGEIF(Movie_analysis_table[Genre],Analysis_1!S24,Movie_analysis_table[imdb_score]) -> 6.99375 | V24: {=MEDIAN(_xlfn._xlws.FILTER(Movie_analysis_table[imdb_score],Movie_analysis_table[Genre]=Analysis_1!S24))} -> 7.2 | W24: {=IFERROR(_xlfn.MODE.SNGL(_xlfn._xlws.FILTER(Movie_analysis_table[imdb_score],Movie_analysis_table[Genre]=Analysis_1!S24)),0)} -> 6.6 | X24: {=IFERROR(MAX(_xlfn._xlws.FILTER(Movie_analysis_table[imdb_score],Movie_analysis_table[Genre]=Analysis_1!S24)),0)} -> 8.5 | Y24: {=IFERROR(MIN(_xlfn._xlws.FILTER(Movie_analysis_table[imdb_score],Movie_analysis_table[Genre]=Analysis_1!S24)),0)} -> 1.6 | Z24: {=IFERROR(VAR(_xlfn._xlws.FILTER(Movie_analysis_table[imdb_score],Movie_analysis_table[Genre]=Analysis_1!S24)),0)} -> 1.4996429 | AA24: {=IFERROR(_xlfn.STDEV.P(_xlfn._xlws.FILTER(Movie_analysis_table[imdb_score],Movie_analysis_table[Genre]=Analysis_1!S24)),0)} -> 1.2149942
S25: Western | T25: 58 | U25: =AVERAGEIF(Movie_analysis_table[Genre],Analysis_1!S25,Movie_analysis_table[imdb_score]) -> 6.7655172 | V25: {=MEDIAN(_xlfn._xlws.FILTER(Movie_analysis_table[imdb_score],Movie_analysis_table[Genre]=Analysis_1!S25))} -> 6.8 | W25: {=IFERROR(_xlfn.MODE.SNGL(_xlfn._xlws.FILTER(Movie_analysis_table[imdb_score],Movie_analysis_table[Genre]=Analysis_1!S25)),0)} -> 6.8 | X25: {=IFERROR(MAX(_xlfn._xlws.FILTER(Movie_analysis_table[imdb_score],Movie_analysis_table[Genre]=Analysis_1!S25)),0)} -> 8.9 | Y25: {=IFERROR(MIN(_xlfn._xlws.FILTER(Movie_analysis_table[imdb_score],Movie_analysis_table[Genre]=Analysis_1!S25)),0)} -> 4.1 | Z25: {=IFERROR(VAR(_xlfn._xlws.FILTER(Movie_analysis_table[imdb_score],Movie_analysis_table[Genre]=Analysis_1!S25)),0)} -> 0.99703569 | AA25: {=IFERROR(_xlfn.STDEV.P(_xlfn._xlws.FILTER(Movie_analysis_table[imdb_score],Movie_analysis_table[Genre]=Analysis_1!S25)),0)} -> 0.98987142
S26: Short | T26: 2 | U26: =AVERAGEIF(Movie_analysis_table[Genre],Analysis_1!S26,Movie_analysis_table[imdb_score]) -> 6.8 | V26: {=MEDIAN(_xlfn._xlws.FILTER(Movie_analysis_table[imdb_score],Movie_analysis_table[Genre]=Analysis_1!S26))} -> 6.8 | W26: {=IFERROR(_xlfn.MODE.SNGL(_xlfn._xlws.FILTER(Movie_analysis_table[imdb_score],Movie_analysis_table[Genre]=Analysis_1!S26)),0)} -> 0 | X26: {=IFERROR(MAX(_xlfn._xlws.FILTER(Movie_analysis_table[imdb_score],Movie_analysis_table[Genre]=Analysis_1!S26)),0)} -> 7.1 | Y26: {=IFERROR(MIN(_xlfn._xlws.FILTER(Movie_analysis_table[imdb_score],Movie_analysis_table[Genre]=Analysis_1!S26)),0)} -> 6.5 | Z26: {=IFERROR(VAR(_xlfn._xlws.FILTER(Movie_analysis_table[imdb_score],Movie_analysis_table[Genre]=Analysis_1!S26)),0)} -> 0.18 | AA26: {=IFERROR(_xlfn.STDEV.P(_xlfn._xlws.FILTER(Movie_analysis_table[imdb_score],Movie_analysis_table[Genre]=Analysis_1!S26)),0)} -> 0.3
S27: Film-Noir | T27: 1 | U27: =AVERAGEIF(Movie_analysis_table[Genre],Analysis_1!S27,Movie_analysis_table[imdb_score]) -> 7.7 | V27: {=MEDIAN(_xlfn._xlws.FILTER(Movie_analysis_table[imdb_score],Movie_analysis_table[Genre]=Analysis_1!S27))} -> 7.7 | W27: {=IFERROR(_xlfn.MODE.SNGL(_xlfn._xlws.FILTER(Movie_analysis_table[imdb_score],Movie_analysis_table[Genre]=Analysis_1!S27)),0)} -> 0 | X27: {=IFERROR(MAX(_xlfn._xlws.FILTER(Movie_analysis_table[imdb_score],Movie_analysis_table[Genre]=Analysis_1!S27)),0)} -> 7.7 | Y27: {=IFERROR(MIN(_xlfn._xlws.FILTER(Movie_analysis_table[imdb_score],Movie_analysis_table[Genre]=Analysis_1!S27)),0)} -> 7.7 | Z27: {=IFERROR(VAR(_xlfn._xlws.FILTER(Movie_analysis_table[imdb_score],Movie_analysis_table[Genre]=Analysis_1!S27)),0)} -> 0 | AA27: {=IFERROR(_xlfn.STDEV.P(_xlfn._xlws.FILTER(Movie_analysis_table[imdb_score],Movie_analysis_table[Genre]=Analysis_1!S27)),0)} -> 0

Sheet Analysis_2
L4: Movie Duration
L6: Mean | M6: Var | N6: STD | O6: Max | P6: Min
L7: =AVERAGE(IMDB_Table[Duration]) -> 109.82712 | M7: =_xlfn.VAR.S(IMDB_Table[Duration]) -> 518.32917 | N7: =_xlfn.STDEV.S(IMDB_Table[Duration]) -> 22.766844 | O7: =MAX(IMDB_Table[Duration]) -> 330 | P7: =MIN(IMDB_Table[Duration]) -> 34

Sheet Analysis_3
T3: Analysis on IMDB Ratings based on Movie Language
A5: Movies Language | B5: Number of Movies | T5: Movies | U5: Count | V5: Mean | W5: Medain | X5: Std
A6: German | B6: 13 | T6: {=_xlfn.UNIQUE(IMDB_Table[language])} -> English | U6: =COUNTIF(IMDB_Table[language],Analysis_3!T6) -> 3603 | V6: =AVERAGEIF(IMDB_Table[language],Analysis_3!T6,IMDB_Table[imdb_score]) -> 6.4204829 | W6: {=MEDIAN(_xlfn._xlws.FILTER(IMDB_Table[imdb_score],IMDB_Table[language]=Analysis_3!T6))} -> 6.5 | X6: {=IFERROR(_xlfn.STDEV.S(_xlfn._xlws.FILTER(IMDB_Table[imdb_score],IMDB_Table[language]=Analysis_3!T6)),"NULL")} -> 1.0526886
A7: Mandarin | B7: 14 | T7: Mandarin | U7: =COUNTIF(IMDB_Table[language],Analysis_3!T7) -> 14 | V7: =AVERAGEIF(IMDB_Table[language],Analysis_3!T7,IMDB_Table[imdb_score]) -> 7.0214286 | W7: {=MEDIAN(_xlfn._xlws.FILTER(IMDB_Table[imdb_score],IMDB_Table[language]=Analysis_3!T7))} -> 7.25 | X7: {=IFERROR(_xlfn.STDEV.S(_xlfn._xlws.FILTER(IMDB_Table[imdb_score],IMDB_Table[language]=Analysis_3!T7)),"NULL")} -> 0.76578624
A8: Spanish | B8: 26 | T8: Aboriginal | U8: =COUNTIF(IMDB_Table[language],Analysis_3!T8) -> 2 | V8: =AVERAGEIF(IMDB_Table[language],Analysis_3!T8,IMDB_Table[imdb_score]) -> 6.95 | W8: {=MEDIAN(_xlfn._xlws.FILTER(IMDB_Table[imdb_score],IMDB_Table[language]=Analysis_3!T8))} -> 6.95 | X8: {=IFERROR(_xlfn.STDEV.S(_xlfn._xlws.FILTER(IMDB_Table[imdb_score],IMDB_Table[language]=Analysis_3!T8)),"NULL")} -> 0.77781746
A9: French | B9: 37 | T9: Spanish | U9: =COUNTIF(IMDB_Table[language],Analysis_3!T9) -> 26 | V9: =AVERAGEIF(IMDB_Table[language],Analysis_3!T9,IMDB_Table[imdb_score]) -> 7.05 | W9: {=MEDIAN(_xlfn._xlws.FILTER(IMDB_Table[imdb_score],IMDB_Table[language]=Analysis_3!T9))} -> 7.15 | X9: {=IFERROR(_xlfn.STDEV.S(_xlfn._xlws.FILTER(IMDB_Table[imdb_score],IMDB_Table[language]=Analysis_3!T9)),"NULL")} -> 0.8261961
A10: English | B10: 3603 | T10: French | U10: =COUNTIF(IMDB_Table[language],Analysis_3!T10) -> 37 | V10: =AVERAGEIF(IMDB_Table[language],Analysis_3!T10,IMDB_Table[imdb_score]) -> 7.2864865 | W10: {=MEDIAN(_xlfn._xlws.FILTER(IMDB_Table[imdb_score],IMDB_Table[language]=Analysis_3!T10))} -> 7.2 | X10: {=IFERROR(_xlfn.STDEV.S(_xlfn._xlws.FILTER(IMDB_Table[imdb_score],IMDB_Table[language]=Analysis_3!T10)),"NULL")} -> 0.56132886
T11: Filipino | U11: =COUNTIF(IMDB_Table[language],Analysis_3!T11) -> 1 | V11: =AVERAGEIF(IMDB_Table[language],Analysis_3!T11,IMDB_Table[imdb_score]) -> 6.7 | W11: {=MEDIAN(_xlfn._xlws.FILTER(IMDB_Table[imdb_score],IMDB_Table[language]=Analysis_3!T11))} -> 6.7 | X11: {=IFERROR(_xlfn.STDEV.S(_xlfn._xlws.FILTER(IMDB_Table[imdb_score],IMDB_Table[language]=Analysis_3!T11)),"NULL")} -> NULL
T12: Maya | U12: =COUNTIF(IMDB_Table[language],Analysis_3!T12) -> 1 | V12: =AVERAGEIF(IMDB_Table[language],Analysis_3!T12,IMDB_Table[imdb_score]) -> 7.8 | W12: {=MEDIAN(_xlfn._xlws.FILTER(IMDB_Table[imdb_score],IMDB_Table[language]=Analysis_3!T12))} -> 7.8 | X12: {=IFERROR(_xlfn.STDEV.S(_xlfn._xlws.FILTER(IMDB_Table[imdb_score],IMDB_Table[language]=Analysis_3!T12)),"NULL")} -> NULL
T13: Kazakh | U13: =COUNTIF(IMDB_Table[language],Analysis_3!T13) -> 1 | V13: =AVERAGEIF(IMDB_Table[language],Analysis_3!T13,IMDB_Table[imdb_score]) -> 6 | W13: {=MEDIAN(_xlfn._xlws.FILTER(IMDB_Table[imdb_score],IMDB_Table[language]=Analysis_3!T13))} -> 6 | X13: {=IFERROR(_xlfn.STDEV.S(_xlfn._xlws.FILTER(IMDB_Table[imdb_score],IMDB_Table[language]=Analysis_3!T13)),"NULL")} -> NULL
T14: Telugu | U14: =COUNTIF(IMDB_Table[language],Analysis_3!T14) -> 1 | V14: =AVERAGEIF(IMDB_Table[language],Analysis_3!T14,IMDB_Table[imdb_score]) -> 8.4 | W14: {=MEDIAN(_xlfn._xlws.FILTER(IMDB_Table[imdb_score],IMDB_Table[language]=Analysis_3!T14))} -> 8.4 | X14: {=IFERROR(_xlfn.STDEV.S(_xlfn._xlws.FILTER(IMDB_Table[imdb_score],IMDB_Table[language]=Analysis_3!T14)),"NULL")} -> NULL
T15: Cantonese | U15: =COUNTIF(IMDB_Table[language],Analysis_3!T15) -> 8 | V15: =AVERAGEIF(IMDB_Table[language],Analysis_3!T15,IMDB_Table[imdb_score]) -> 7.2375 | W15: {=MEDIAN(_xlfn._xlws.FILTER(IMDB_Table[imdb_score],IMDB_Table[language]=Analysis_3!T15))} -> 7.3 | X15: {=IFERROR(_xlfn.STDEV.S(_xlfn._xlws.FILTER(IMDB_Table[imdb_score],IMDB_Table[language]=Analysis_3!T15)),"NULL")} -> 0.44057592
T16: Japanese | U16: =COUNTIF(IMDB_Table[language],Analysis_3!T16) -> 12 | V16: =AVERAGEIF(IMDB_Table[language],Analysis_3!T16,IMDB_Table[imdb_score]) -> 7.625 | W16: {=MEDIAN(_xlfn._xlws.FILTER(IMDB_Table[imdb_score],IMDB_Table[language]=Analysis_3!T16))} -> 7.8 | X16: {=IFERROR(_xlfn.STDEV.S(_xlfn._xlws.FILTER(IMDB_Table[imdb_score],IMDB_Table[language]=Analysis_3!T16)),"NULL")} -> 0.89962113
T17: Aramaic | U17: =COUNTIF(IMDB_Table[language],Analysis_3!T17) -> 1 | V17: =AVERAGEIF(IMDB_Table[language],Analysis_3!T17,IMDB_Table[imdb_score]) -> 7.1 | W17: {=MEDIAN(_xlfn._xlws.FILTER(IMDB_Table[imdb_score],IMDB_Table[language]=Analysis_3!T17))} -> 7.1 | X17: {=IFERROR(_xlfn.STDEV.S(_xlfn._xlws.FILTER(IMDB_Table[imdb_score],IMDB_Table[language]=Analysis_3!T17)),"NULL")} -> NULL
T18: Italian | U18: =COUNTIF(IMDB_Table[language],Analysis_3!T18) -> 7 | V18: =AVERAGEIF(IMDB_Table[language],Analysis_3!T18,IMDB_Table[imdb_score]) -> 7.1857143 | W18: {=MEDIAN(_xlfn._xlws.FILTER(IMDB_Table[imdb_score],IMDB_Table[language]=Analysis_3!T18))} -> 7 | X18: {=IFERROR(_xlfn.STDEV.S(_xlfn._xlws.FILTER(IMDB_Table[imdb_score],IMDB_Table[language]=Analysis_3!T18)),"NULL")} -> 1.155319
T19: Dutch | U19: =COUNTIF(IMDB_Table[language],Analysis_3!T19) -> 3 | V19: =AVERAGEIF(IMDB_Table[language],Analysis_3!T19,IMDB_Table[imdb_score]) -> 7.5666667 | W19: {=MEDIAN(_xlfn._xlws.FILTER(IMDB_Table[imdb_score],IMDB_Table[language]=Analysis_3!T19))} -> 7.8 | X19: {=IFERROR(_xlfn.STDEV.S(_xlfn._xlws.FILTER(IMDB_Table[imdb_score],IMDB_Table[language]=Analysis_3!T19)),"NULL")} -> 0.40414519
T20: Dari | U20: =COUNTIF(IMDB_Table[language],Analysis_3!T20) -> 2 | V20: =AVERAGEIF(IMDB_Table[language],Analysis_3!T20,IMDB_Table[imdb_score]) -> 7.5 | W20: {=MEDIAN(_xlfn._xlws.FILTER(IMDB_Table[imdb_score],IMDB_Table[language]=Analysis_3!T20))} -> 7.5 | X20: {=IFERROR(_xlfn.STDEV.S(_xlfn._xlws.FILTER(IMDB_Table[imdb_score],IMDB_Table[language]=Analysis_3!T20)),"NULL")} -> 0.14142136
T21: German | U21: =COUNTIF(IMDB_Table[language],Analysis_3!T21) -> 13 | V21: =AVERAGEIF(IMDB_Table[language],Analysis_3!T21,IMDB_Table[imdb_score]) -> 7.6923077 | W21: {=MEDIAN(_xlfn._xlws.FILTER(IMDB_Table[imdb_score],IMDB_Table[language]=Analysis_3!T21))} -> 7.7 | X21: {=IFERROR(_xlfn.STDEV.S(_xlfn._xlws.FILTER(IMDB_Table[imdb_score],IMDB_Table[language]=Analysis_3!T21)),"NULL")} -> 0.64091281
T22: Mongolian | U22: =COUNTIF(IMDB_Table[language],Analysis_3!T22) -> 1 | V22: =AVERAGEIF(IMDB_Table[language],Analysis_3!T22,IMDB_Table[imdb_score]) -> 7.3 | W22: {=MEDIAN(_xlfn._xlws.FILTER(IMDB_Table[imdb_score],IMDB_Table[language]=Analysis_3!T22))} -> 7.3 | X22: {=IFERROR(_xlfn.STDEV.S(_xlfn._xlws.FILTER(IMDB_Table[imdb_score],IMDB_Table[language]=Analysis_3!T22)),"NULL")} -> NULL
... T43: Swedish | U43: =COUNTIF(IMDB_Table[language],Analysis_3!T43) -> 1 | V43: =AVERAGEIF(IMDB_Table[language],Analysis_3!T43,IMDB_Table[imdb_score]) -> 7.6 | W43: {=MEDIAN(_xlfn._xlws.FILTER(IMDB_Table[imdb_score],IMDB_Table[language]=Analysis_3!T43))} -> 7.6 | X43: {=IFERROR(_xlfn.STDEV.S(_xlfn._xlws.FILTER(IMDB_Table[imdb_score],IMDB_Table[language]=Analysis_3!T43)),"NULL")} -> NULL

Sheet Analysis_4
B4: Director | C4: Movies Count | D4: Avg_IMDB
B5: Christopher Nolan | C5: 8 | D5: 8.425
B6: Quentin Tarantino | C6: 8 | D6: 8.2
B7: James Cameron | C7: 7 | D7: 7.9142857
B8: Peter Jackson | C8: 9 | D8: 7.8888889
B9: Andrew Stanton | C9: 3 | D9: 7.7333333
B10: Alejandro G. | C10: 5 | D10: 7.84
B11: Nathan Greno | C11: 1 | D11: 7.8
B12: Joss Whedon | C12: 3 | D12: 7.8666667
B13: David Yates | C13: 3 | D13: 7.2
B14: David Fincher | C14: 10 | D14: 7.75
B15: Martin Scorsese | C15: 16 | D15: 7.675
B16: Francis Ford Coppola | C16: 9 | D16: 7.6555556
... B1752: Neill Dela Llana | C1752: 1 | D1752: 6.3

Sheet Analysis_5
A3: Row Labels | B3: Sum of net_profit
A4: The Hunger Games | B4: 329999255
A5: The Dark Knight | B5: 348316061
A6: Star Wars: Episode I - The Phantom Menace | B6: 359544677
A7: The Lion King | B7: 377783777
A8: The Avengers | B8: 403279547
A9: E.T. The Extra-Terrestrial | B9: 424449459
A10: Star Wars: Episode Iv - A New Hope | B10: 449935665
A11: Titanic | B11: 458672302
A12: Jurassic World | B12: 502177271
A13: Avatar | B13: 523505847
A16: Correlation between Gross and Budget | B16: =CORREL(IMDB_Table[budget],IMDB_Table[gross]) -> 0.096418263
A17: Highest Profit Margin | B17: =MAX(IMDB_Table[net_profit]) -> 523505847

Sheet Dashboard
